DXEntity/__init__.py
DXEntity/_dxentity.py
DXEntity/_version.py
DXEntity/py.typed
DXEntity-0.1.8.dist-info/LICENSE
DXEntity-0.1.8.dist-info/METADATA
DXEntity-0.1.8.dist-info/WHEEL
DXEntity-0.1.8.dist-info/top_level.txt
DXEntity-0.1.8.dist-info/RECORD
