Metadata-Version: 2.1
Name: DXEntity
Version: 0.1.8
Summary: The DXEntity API return location information for an amateur radio call sign.
Author: Fred C.
License: BSD 3-Clause License
Project-URL: Source, https://github.com/0x9900/DXEntity
Project-URL: Tracker, https://github.com/0x9900/DXEntity/issues
Classifier: Development Status :: 4 - Beta
Classifier: Intended Audience :: Developers
Classifier: License :: OSI Approved :: BSD License
Classifier: Operating System :: MacOS
Classifier: Operating System :: POSIX :: Linux
Classifier: Programming Language :: Python :: 3.10
Classifier: Programming Language :: Python :: 3.11
Classifier: Programming Language :: Python
Classifier: Topic :: Communications :: Ham Radio
Requires-Python: >=3.10
License-File: LICENSE
